setup.cfg
setup.py
lightwsgi/__init__.py
lightwsgi/__main__.py
lightwsgi/cookie.py
lightwsgi.egg-info/PKG-INFO
lightwsgi.egg-info/SOURCES.txt
lightwsgi.egg-info/dependency_links.txt
lightwsgi.egg-info/top_level.txt