Metadata-Version: 1.0
Name: lightwsgi
Version: 1.0
Summary: A small, simple and lightweight WSGI framework and helpers.
Home-page: UNKNOWN
Author: Louis Young
Author-email: louispryoung@gmail.com
License: UNKNOWN
Keywords: wsgi,framework,lightweight,apache
Platform: UNKNOWN
